<?xml version="1.0" encoding="UTF-8"?>
<!--
This file is part of the DITA Open Toolkit project.

Copyright 2004, 2005 IBM Corporation

See the accompanying LICENSE file for applicable license.
-->
<?xml-model href="strings.rnc" type="application/relax-ng-compact-syntax"?>
<variables>
   <variable id="Figure">Figura</variable>
   <variable id="Table">Tabla</variable>
   <variable id="Next topic">Tema siguiente</variable>
   <variable id="Previous topic">Tema anterior</variable>
   <variable id="Parent topic">Tema principal</variable>
   <variable id="Required cleanup">Por revisar</variable>
   <variable id="Draft comment">Borrador: comentarios</variable>
   <variable id="Option">Opción</variable>
   <variable id="Description">Descripción</variable>
   <variable id="Optional">Opcional</variable>
   <variable id="Required">Necesario</variable>
   <variable id="Skip visual syntax diagram">Omitir el esquema de sintaxis visual</variable>
   <variable id="Read syntax diagram">Leer el esquema de sintaxis</variable>
   <variable id="Start of change">Inicio del cambio</variable>
   <variable id="End of change">Fin del cambio</variable>
   <variable id="Index">Índice</variable>
   <variable id="Special characters">Caracteres Especiales</variable>
   <variable id="Numerics">Números</variable>
   <variable id="End notes">Notas al pie</variable>
   <variable id="Artwork">Gráficos e imágenes</variable>
   <variable id="Syntax">Sintaxis</variable>
   <variable id="Type">Tipo</variable>
   <variable id="Value">Valor</variable>
   <variable id="intro-to-topic-link">apartado</variable>
   <variable id="Note">Nota</variable>
   <variable id="Notes">Notas</variable>
   <variable id="Notice">Notice</variable><!--TODO:Notice-->
   <variable id="Tip">Consejo</variable>
   <variable id="Fastpath">Vía de acceso rápida</variable>
   <variable id="Important">Importante</variable>
   <variable id="Attention">Atención</variable>
   <variable id="Caution">PRECAUCIÓN</variable>
   <variable id="Danger">PELIGRO</variable>
   <variable id="Remember">Recuerde</variable>
   <variable id="Restriction">Restricción</variable>
   <variable id="Trouble">Problema</variable>
   <variable id="Warning">Aviso</variable>
   <variable id="Contents">Contenido</variable>
   <variable id="Related concepts">Conceptos relacionados</variable>
   <variable id="Related tasks">Tareas relacionadas</variable>
   <variable id="Related reference">Referencia relacionada</variable>
   <variable id="Related information">Información relacionada</variable>
   <variable id="Prerequisite">Requisito</variable>
   <variable id="Prerequisites">Requisitos</variable>
   <variable id="or">or</variable>
   <variable id="task_prereq">Antes de empezar</variable>
   <variable id="task_context">Por qué y cuándo se efectúa esta tarea</variable>
   <variable id="task_example">Ejemplo</variable>
   <variable id="task_postreq">Qué hacer a continuación</variable>
   <variable id="task_procedure">Procedimiento</variable>
   <variable id="task_procedure_unordered">Procedimiento</variable>
   <variable id="task_results">Resultados</variable>
   <variable id="Copyright">Copyright</variable>
   <variable id="OpenQuote">«</variable>
   <variable id="CloseQuote">»</variable>
   <variable id="a11y.and-then"/>
</variables>
